{"song":{"1":"Everything (Amen)","2":"Jehovah Overdo","3":"Congratulations (feat. Buchi)","4":"Worship Your Maker","5":"Omemma","6":"Excess Love (feat. J.J. Hairston & Youthful Praise) [Remix]","7":"All That Matters","8":"Too Faithful","9":"All The Glory","10":"Open Doors","11":"Yahweh Yahweh (feat. Sinach)","12":"Olorun Agbaye - You Are Mighty (feat. Chandler Moore & O\/B\/A)","13":"Never Go Down ft. Limoblaze","14":"Adom Grace","15":"Amazing God","16":"Beautiful (feat. Nathaniel Bassey)","17":"Yahweh","18":"You are Yahweh","19":"Hosanna (Live)","20":"Obinasom","21":"Way Maker","22":"Now","23":"Jesus (feat. Mercy Chinwo)","24":"Suddenly","25":"Covenant Keeping God","26":"You are Great","27":"Onyedikagi (feat. Glowrie)","28":"Fragrance to Fire","29":"Omeriwo (feat. Henrisoul & Mercy Chinwo)","30":"Chinedum","31":"At All Cost","32":"NO OTHER NAME","33":"Yes And Amen","34":"Nara (feat. Travis Greene)","35":"You Are Worthy","36":"Na You Dey Reign","37":"More Than Gold","38":"Hallelujah No Go Finish","39":"In Your Hands","40":"Mighty God (feat. Nathaniel Bassey)","41":"God of Vengeance","42":"Imela","43":"Halleluyah","44":"Bigger Everyday","45":"Under The Canopy","46":"All Things Are Ready","47":"Only One ft. Masauti","48":"More Than Enough","49":"Strong Tower","50":"Hallelujah Challenge Praise Medley"},"artist":{"1":"Timi Dakolo","2":"Chidinma","3":"Ada Ehi","4":"Dunsin Oyekan","5":"Sinach","6":"Mercy Chinwo","7":"Minister GUC","8":"Moses Bliss","9":"Da Voice","10":"Ada Ehi","11":"Nathaniel Bassey","12":"Nathaniel Bassey","13":"Ada Ehi","14":"Diana Hamilton","15":"Mercy Chinwo","16":"Sinach","17":"EBEN","18":"Steve Crown","19":"Steve Crown","20":"Mercy Chinwo","21":"Sinach","22":"Ada Ehi","23":"Samsong","24":"Mercy Chinwo","25":"Jimmy D Psalmist","26":"Steve Crown","27":"Mercy Chinwo","28":"Dunsin Oyekan","29":"Sammie Okposo","30":"Mercy Chinwo","31":"Dunsin Oyekan","32":"Frank Edwards","33":"Tope Alabi","34":"Tim Godfrey","35":"Tope Alabi","36":"Mercy Chinwo","37":"Judith Kanayo","38":"Freke Umoh","39":"Moses Bliss","40":"Steve Crown","41":"Minister GUC","42":"Steve Crown","43":"Tope Alabi","44":"Moses Bliss","45":"Frank Edwards","46":"Sinach","47":"Mr. Seed","48":"Ada Ehi","49":"Nathaniel Bassey","50":"Nathaniel Bassey"},"Previous week":{"1":1,"2":3,"3":2,"4":4,"5":5,"6":7,"7":43,"8":8,"9":0,"10":6,"11":10,"12":9,"13":12,"14":11,"15":13,"16":24,"17":17,"18":16,"19":14,"20":18,"21":20,"22":15,"23":23,"24":21,"25":22,"26":25,"27":19,"28":27,"29":0,"30":33,"31":31,"32":32,"33":30,"34":34,"35":35,"36":36,"37":29,"38":37,"39":39,"40":41,"41":0,"42":42,"43":44,"44":40,"45":46,"46":45,"47":47,"48":48,"49":0,"50":49},"weeks on chart":{"1":14,"2":14,"3":13,"4":13,"5":14,"6":13,"7":14,"8":13,"9":1,"10":11,"11":14,"12":14,"13":8,"14":13,"15":13,"16":3,"17":13,"18":14,"19":12,"20":13,"21":12,"22":14,"23":14,"24":14,"25":14,"26":14,"27":14,"28":14,"29":1,"30":12,"31":13,"32":12,"33":12,"34":10,"35":9,"36":14,"37":14,"38":4,"39":11,"40":9,"41":1,"42":14,"43":3,"44":11,"45":7,"46":7,"47":2,"48":4,"49":1,"50":2}}