{"album":{"1":"19 & Dangerous","2":"High Tension 2.0","3":"Eclipse","4":"High Tension","5":"Water & Garri","6":"LV N ATTN","7":"Twice As Tall","8":"Cultural Praise","9":"Man Of Galilee","10":"WONDALAND","11":"What Have We Done","12":"All or Nothing","13":"Kpos Lifestyle, Vol. 1","14":"THE GOAT","15":"Euphoria","16":"Roots","17":"Jackboy 2","18":"UY Scuti","19":"Before We Fall Asleep","20":"APOLLO","21":"Made In Lagos: Deluxe Edition","22":"Donda","23":"Somewhere Between Beauty & Magic","24":"Laughter, Tears & Goosebumps","25":"Please Excuse Me for Being Antisocial","26":"Boo of the Booless","27":"Get Layd","28":"Carpe Diem","29":"Sex Over Love","30":"Superstar","31":"We're All Alone In This Together","32":"The Voice of the Heroes","33":"Nothing To Prove","34":"Boyfriend","35":"African Giant","36":"SATISFIED","37":"Justice","38":"Zero Panic","39":"Legends Never Die","40":"For Broken Ears","41":"Simisola","42":"9: Harmattan & Winter","43":"Alari","44":"Shoot For The Stars Aim For The Moon","45":"Death Race For Love","46":"Afro Pop Vol. 1","47":"Light","48":"Just Cause Y'all Waited 2 (Deluxe)","49":"Top","50":"Shopla","51":"SoulFly (Deluxe Version)","52":"Hall of Fame","53":"High Off Life","54":"KillaXtra","55":"Moon Boy","56":"Happier Than Ever","57":"All That Matters","58":"The Message","59":"Outside","60":"My Turn (Deluxe)","61":"Faith","62":"...Shall We Begin...","63":"PSYCHODRAMA","64":"Just A Matter of Slime","65":"OXYGENE","66":"Yabasi","67":"Wild West","68":"A True Champion","69":"SAVAGE MODE II","70":"Rema Freestyle EP","71":"We Love You Tecca 2","72":"Meet The Woo 2","73":"Haitian Boy Kodak","74":"I LOVE GIRLS WITH TROBUL","75":"WUNNA","76":"Hollywood's Bleeding","77":"Trip At Knight (Complete Edition)","78":"Goodbye & Good Riddance","79":"Slime Language 2 (Deluxe)","80":"The Human Condition","81":"The Palmwine Express","82":"JESUS IS KING","83":"Scorpion","84":"If Summer Happened","85":"3 Th3 Album","86":"DAMN.","87":"Tribl I","88":"TOP MEMBA","89":"Spontaneous Praise, Vol. 1","90":"Clone Wars Vol. 5 - The Algorhythm","91":"Future Hndrxx Presents: The WIZRD","92":"Certified Lover Boy","93":"King Of Love","94":"PANDEMIC","95":"No Pressure","96":"NEW ERA","97":"A Better Time","98":"Three","99":"The Gospel of the Kingdom","100":"Twelve A.M"},"artist":{"1":"Ayra Starr","2":"Dangbana Republik & Bella Shmurda","3":"Troniq Music & Oxlade","4":"Bella Shmurda","5":"Tiwa Savage","6":"Lojay & Sarz","7":"Burna Boy","8":"KCee & Okwesili Eze Group","9":"Judikay","10":"Teni","11":"Omah Lay","12":"Rotimi","13":"Ajebo Hustlers","14":"Polo G","15":"PsychoYP","16":"The Cavemen.","17":"Jackboy","18":"Olamide","19":"Johnny Drille","20":"Fireboy DML","21":"Wizkid","22":"Kanye West","23":"Joeboy","24":"Fireboy DML","25":"Roddy Ricch","26":"Chike","27":"Omah Lay","28":"Olamide","29":"Blaqbonez","30":"Wizkid","31":"Dave","32":"Lil Baby & Lil Durk","33":"Victor AD","34":"CKay","35":"Burna Boy","36":"Mercy Chinwo","37":"Justin Bieber","38":"Balloranking","39":"Juice WRLD","40":"Tems","41":"Simi","42":"Brymo","43":"Liya","44":"Pop Smoke","45":"Juice WRLD","46":"Adekunle Gold","47":"MohBad","48":"Lil Durk","49":"YoungBoy Never Broke Again","50":"Jaido P","51":"Rod Wave","52":"Polo G","53":"Future","54":"Killertunes","55":"Yung Bleu","56":"Billie Eilish","57":"Ayanfe","58":"Minister GUC","59":"Burna Boy","60":"Lil Baby","61":"Pop Smoke","62":"Laycon","63":"Dave","64":"YNW Melly","65":"Oxlade","66":"Basketmouth","67":"Central Cee","68":"Rexxie","69":"21 Savage & Metro Boomin","70":"Rema","71":"Lil Tecca","72":"Pop Smoke","73":"Kodak Black","74":"Sarz X WurlD","75":"Gunna","76":"Post Malone","77":"Trippie Redd","78":"Juice WRLD","79":"Young Stoner Life, Young Thug & Gunna","80":"Jon Bellion","81":"Show Dem Camp","82":"Kanye West","83":"Drake","84":"Laime","85":"Not3s","86":"Kendrick Lamar","87":"Tribl & Maverick City Music","88":"Kida Kudz","89":"Laolu Gbenjo","90":"The Algorhythm - Show Dem Camp","91":"Future","92":"Drake","93":"Kizz Daniel","94":"Ruger","95":"Sarkodie","96":"Kiss Daniel","97":"Davido","98":"Patoranking","99":"Dunsin Oyekan","100":"Crayon"},"Previous week":{"1":1,"2":2,"3":3,"4":8,"5":4,"6":5,"7":6,"8":15,"9":10,"10":9,"11":11,"12":7,"13":13,"14":14,"15":12,"16":17,"17":18,"18":22,"19":21,"20":24,"21":26,"22":25,"23":28,"24":27,"25":29,"26":23,"27":32,"28":36,"29":35,"30":42,"31":31,"32":33,"33":30,"34":41,"35":37,"36":38,"37":39,"38":59,"39":43,"40":47,"41":46,"42":0,"43":40,"44":49,"45":48,"46":50,"47":19,"48":52,"49":58,"50":16,"51":57,"52":55,"53":56,"54":0,"55":45,"56":54,"57":34,"58":60,"59":65,"60":61,"61":44,"62":63,"63":68,"64":20,"65":67,"66":74,"67":82,"68":64,"69":73,"70":70,"71":79,"72":71,"73":80,"74":75,"75":81,"76":83,"77":66,"78":72,"79":86,"80":95,"81":93,"82":76,"83":88,"84":96,"85":78,"86":89,"87":100,"88":0,"89":0,"90":97,"91":0,"92":0,"93":51,"94":0,"95":0,"96":0,"97":0,"98":0,"99":0,"100":0},"weeks on chart":{"1":5,"2":9,"3":4,"4":10,"5":5,"6":13,"7":13,"8":13,"9":13,"10":13,"11":13,"12":3,"13":7,"14":13,"15":4,"16":2,"17":3,"18":12,"19":2,"20":13,"21":3,"22":3,"23":13,"24":13,"25":13,"26":13,"27":13,"28":13,"29":13,"30":13,"31":6,"32":13,"33":6,"34":13,"35":13,"36":7,"37":13,"38":2,"39":13,"40":13,"41":4,"42":1,"43":4,"44":3,"45":13,"46":3,"47":3,"48":3,"49":13,"50":4,"51":4,"52":13,"53":13,"54":1,"55":7,"56":6,"57":2,"58":13,"59":6,"60":3,"61":5,"62":13,"63":3,"64":5,"65":13,"66":13,"67":13,"68":10,"69":13,"70":3,"71":3,"72":3,"73":13,"74":3,"75":7,"76":4,"77":4,"78":3,"79":4,"80":2,"81":13,"82":3,"83":3,"84":2,"85":3,"86":2,"87":2,"88":1,"89":1,"90":6,"91":1,"92":1,"93":2,"94":1,"95":1,"96":1,"97":1,"98":1,"99":1,"100":1}}